nertivia/__init__.py
nertivia-0.3.0.dist-info/METADATA
nertivia-0.3.0.dist-info/WHEEL
nertivia-0.3.0.dist-info/top_level.txt
nertivia-0.3.0.dist-info/RECORD
